README.md
setup.py
estest/__init__.py
estest/assignment_test.py
estest/compilers.py
estest/error_handling_test.py
estest/exceptions.py
estest/language_codes.py
estest/so_builder.py
estest.egg-info/PKG-INFO
estest.egg-info/SOURCES.txt
estest.egg-info/dependency_links.txt
estest.egg-info/top_level.txt