Metadata-Version: 2.1
Name: estest
Version: 1.0.3
Summary: A simple testing framework
Home-page: UNKNOWN
Author: Salimgereyev Adi
Author-email: <adisalimgereev@gmail.com>
License: UNKNOWN
Keywords: python,testing,c,c++
Platform: UNKNOWN
Classifier: Development Status :: 1 - Planning
Classifier: Intended Audience :: Developers
Classifier: Programming Language :: Python :: 3
Classifier: Operating System :: Unix
Classifier: Operating System :: MacOS :: MacOS X
Classifier: Operating System :: Microsoft :: Windows
